{"version": "4.5.6", "flags": {}, "shapes": [{"label": "broccoli", "line_color": null, "fill_color": null, "points": [[730, 710], [730, 804]], "shape_type": "circle", "flags": {}}, {"label": "broccoli", "line_color": null, "fill_color": null, "points": [[623, 250], [623, 355]], "shape_type": "circle", "flags": {}}], "lineColor": [0, 255, 0, 128], "fillColor": [255, 0, 0, 128], "imagePath": "20200713_151619747474_plant1079_rgb_trigger005.png", "imageData": null, "imageHeight": 1280, "imageWidth": 1280}